{"tfjsVersion":"1.3.1","tmVersion":"2.4.7","packageVersion":"0.8.4-alpha2","packageName":"@teachablemachine/image","timeStamp":"2023-10-21T14:12:20.622Z","userMetadata":{},"modelName":"tm-my-image-model","labels":["Adidas_Eqt_Support_Adv","Adidas_Ultrabounce_Women","Adidas_Yeezy_350","Asics_Jolt_3","Asics_Metarise","Asics_Tri_Noosa_13","Converse_Chuck_Taylor_All_Star_Hi_Top","Converse_Chuck_Taylor_Low","Converse_Run_Star_Hike","Crocs_Classic_Clog","Crocs_Literide","Crocs_Mega_Crush","New_Balance_420","New_Balance_990","New_Balance_FuelCell","Nike_Air_Force_1_Low","Nike_Air_Jordan","Nike_Air_Max_97","Puma_Interflex_Modern","Puma_Relax_Knit_Slip_On","Puma_Suede","Reebok_Royal_BB4500","Reebok_Royal_Complete_3","Reebok_Zig_Dynamica","Skechers_DLites","Skechers_Go_Walk","Skechers_Statement"],"imageSize":224}